LICENSE.txt
README.md
setup.cfg
setup.py
disc2radmc/__init__.py
disc2radmc/constants.py
disc2radmc/functions_misc.py
disc2radmc/model.py
disc2radmc.egg-info/PKG-INFO
disc2radmc.egg-info/SOURCES.txt
disc2radmc.egg-info/dependency_links.txt
disc2radmc.egg-info/requires.txt
disc2radmc.egg-info/top_level.txt